ractorlabs/__init__.py
ractorlabs/_base_client.py
ractorlabs/_client.py
ractorlabs/_compat.py
ractorlabs/_constants.py
ractorlabs/_exceptions.py
ractorlabs/_files.py
ractorlabs/_models.py
ractorlabs/_qs.py
ractorlabs/_resource.py
ractorlabs/_response.py
ractorlabs/_streaming.py
ractorlabs/_types.py
ractorlabs/_version.py
ractorlabs/py.typed
ractorlabs/_utils/__init__.py
ractorlabs/_utils/_compat.py
ractorlabs/_utils/_datetime_parse.py
ractorlabs/_utils/_logs.py
ractorlabs/_utils/_proxy.py
ractorlabs/_utils/_reflection.py
ractorlabs/_utils/_resources_proxy.py
ractorlabs/_utils/_streams.py
ractorlabs/_utils/_sync.py
ractorlabs/_utils/_transform.py
ractorlabs/_utils/_typing.py
ractorlabs/_utils/_utils.py
ractorlabs/lib/.keep
ractorlabs/resources/__init__.py
ractorlabs/resources/auth.py
ractorlabs/resources/blocklist.py
ractorlabs/resources/operators.py
ractorlabs/resources/responses.py
ractorlabs/resources/version.py
ractorlabs/resources/published/__init__.py
ractorlabs/resources/published/published.py
ractorlabs/resources/published/sessions.py
ractorlabs/resources/sessions/__init__.py
ractorlabs/resources/sessions/context.py
ractorlabs/resources/sessions/responses.py
ractorlabs/resources/sessions/sessions.py
ractorlabs/resources/sessions/files/__init__.py
ractorlabs/resources/sessions/files/files.py
ractorlabs/types/__init__.py
ractorlabs/types/auth_create_token_params.py
ractorlabs/types/auth_retrieve_current_principal_response.py
ractorlabs/types/blocklist_block_params.py
ractorlabs/types/blocklist_block_response.py
ractorlabs/types/blocklist_list_response.py
ractorlabs/types/blocklist_unblock_params.py
ractorlabs/types/blocklist_unblock_response.py
ractorlabs/types/login_response.py
ractorlabs/types/operator.py
ractorlabs/types/operator_create_params.py
ractorlabs/types/operator_list_response.py
ractorlabs/types/operator_login_params.py
ractorlabs/types/operator_update_params.py
ractorlabs/types/operator_update_password_params.py
ractorlabs-1.0.0.dist-info/METADATA
ractorlabs-1.0.0.dist-info/WHEEL
ractorlabs-1.0.0.dist-info/licenses/LICENSE
ractorlabs-1.0.0.dist-info/RECORD
